Workbook

Sheet Accueil
B2: CARTE DE MEMBRE — CONSEIL NATIONAL DE L'ENTREPRENEURIAT (CN)
B3: Réseau mutualisé de services premium pour chefs d'entreprise | Sénégal & Afrique de l'Ouest
B5: LE PRINCIPE — l'assurance appliquée au réseau d'affaires
B6: Le membre paie une cotisation TRÈS accessible et accède à un réseau d'avantages négociés
B7: dans de multiples branches : assurance, BTP, business lounge, aviation, conseil & expertise
B8: comptable, santé, formation, financement, mobilité, juridique, digital, télécom…
B10: L'accessibilité repose sur un principe actuariel : TOUS les membres ne consomment PAS
B11: TOUS les services. La probabilité de consommation de chaque service est faible, donc le coût
B12: réel MUTUALISÉ par membre reste bien inférieur à la valeur faciale des avantages offerts.
B13: La cotisation couvre le coût mutualisé + les frais + une marge ; la valeur perçue, elle,
B14: est plusieurs fois supérieure au prix payé.
B16: CHIFFRES CLÉS DU PRÉVISIONNEL (36 mois)
B17: Membres actifs — mois 1 & 2 | D17: ='Previsionnel_Membres'!B4
B18: Membres actifs — cap. franchi (500+) | D18: ='Previsionnel_Membres'!B39
B19: Cotisation Essentiel / an | D19: =Hypotheses!B4
B20: Cotisation Business / an | D20: =Hypotheses!B5
B21: Cotisation Élite / an | D21: =Hypotheses!B6
B22: Revenu total mois 36 | D22: ='Compte_Resultat'!F39
B23: Résultat mensuel mois 36 | D23: ='Compte_Resultat'!I39
B24: Résultat cumulé à 36 mois | D24: ='Compte_Resultat'!J39
B26: SOMMAIRE DES FEUILLES
B27: ▸ Architecture_Services | C27: Les 15 branches du réseau, partenaires cibles, accès par formule
B28: ▸ Hypotheses | C28: Tous les paramètres modifiables : prix, mix, churn, OPEX
B29: ▸ Modele_Actuariel | C29: Cœur du modèle : probabilité de consommation → coût mutualisé
B30: ▸ Previsionnel_Membres | C30: Croissance des adhérents sur 36 mois (20 → 850+)
B31: ▸ Compte_Resultat | C31: P&L mensuel : revenus, coûts services, OPEX, résultat
B32: ▸ Tableau_de_Bord | C32: KPIs, ratios, seuil de rentabilité, graphiques
B33: ▸ Feuille_de_Route | C33: Déploiement en 4 phases + prochaines actions

Sheet Architecture_Services
A1: ARCHITECTURE DU RÉSEAU — 15 BRANCHES DE SERVICES
A3: # | B3: Branche | C3: Bénéfice pour le membre | D3: Partenaires cibles (SN / Afrique de l'Ouest) | E3: Essent. | F3: Busin. | G3: Élite
A4: 1 | B4: Assurance & Prévoyance | C4: Santé, auto, RC pro, prévoyance à tarif groupe négocié | D4: SUNU, SONAM, AXA SN, Allianz, Amsa, NSIA | E4: — | F4: ✔ | G4: ✔
A5: 2 | B5: BTP & Construction | C5: Remises études, matériaux, main d'œuvre, expertise chantier | D5: Cimenteries (Dangote, Sococim), quincailleries, BET | E5: — | F5: — | G5: ✔
A6: 3 | B6: Business Lounge | C6: Salons aéroport AIBD, espaces coworking & réunion premium | D6: AIBD Premium, lounges hôtels, coworking Dakar | E6: ✔ (limité) | F6: ✔ | G6: ✔
A7: 4 | B7: Aviation | C7: Billets négociés, surclassements, jet & aviation d'affaires | D7: Air Sénégal, agences IATA, brokers jet | E7: — | F7: ✔ | G7: ✔
A8: 5 | B8: Conseil & Expertise comptable | C8: Comptabilité, fiscal, audit, création & structuration | D8: Cabinets OECCA, fiduciaires, ONECCA | E8: ✔ | F8: ✔ | G8: ✔
A9: 6 | B9: Santé & Bien-être | C9: Télémédecine, check-ups, cliniques partenaires | D9: Cliniques Dakar, plateformes e-santé | E9: ✔ | F9: ✔ | G9: ✔
A10: 7 | B10: CN Academy — Formation | C10: Formations, certifications, mentorat dirigeants | D10: Écoles de commerce, ISM, CESAG, coachs | E10: ✔ | F10: ✔ | G10: ✔
A11: 8 | B11: Financement & Crédit | C11: Mise en relation banques/fonds, montage dossier, garanties | D11: Banques, FONGIP, DER/FJ, fonds PME | E11: — | F11: ✔ | G11: ✔
A12: 9 | B12: Voyage & Hôtellerie | C12: Tarifs corporate hôtels, per diem & séjours négociés | D12: Chaînes hôtelières, agences de voyage | E12: — | F12: ✔ | G12: ✔
A13: 10 | B13: Mobilité Premium | C13: VTC dirigeant, location véhicules avec chauffeur | D13: Loueurs, flottes VTC premium | E13: ✔ | F13: ✔ | G13: ✔
A14: 11 | B14: Juridique & Contentieux | C14: Avocats, contrats, recouvrement, propriété intellectuelle | D14: Cabinets d'avocats, huissiers | E14: — | F14: — | G14: ✔
A15: 12 | B15: Digital & Marketing | C15: Sites, branding, community management, publicité | D15: Agences digitales (ex. écosystème C Carré) | E15: ✔ (limité) | F15: ✔ | G15: ✔
... A18: 15 | B18: Télécom & Connectivité | C18: Forfaits pro, internet entreprise, Starlink | D18: Waw Telecom / Starlink, opérateurs | E18: ✔ | F18: ✔ | G18: ✔
A20: LES 3 FORMULES DE CARTE
B21: CN ESSENTIEL | C21: CN BUSINESS | D21: CN ÉLITE
A22: Cible | B22: Jeune entrepreneur / TPE | C22: PME établie / dirigeant | D22: Grand compte / dirigeant premium
A23: Cotisation / an | B23: =Hypotheses!B4 | C23: =Hypotheses!B5 | D23: =Hypotheses!B6
A24: Cotisation / mois | B24: =Hypotheses!B4/12 | C24: =Hypotheses!B5/12 | D24: =Hypotheses!B6/12
A25: Branches accessibles | B25: 8 branches | C25: 13 branches | D25: 15 branches (toutes)
A26: Valeur faciale réseau/an | B26: ='Modele_Actuariel'!K19 | C26: ='Modele_Actuariel'!L19 | D26: ='Modele_Actuariel'!M19

Sheet Hypotheses
A1: HYPOTHÈSES — paramètres modifiables (cellules en or)
A3: TARIFICATION (cotisation annuelle, FCFA)
A4: CN Essentiel | B4: 60000 | D4: ≈ 5 000 FCFA / mois — très accessible
A5: CN Business | B5: 180000 | D5: ≈ 15 000 FCFA / mois
A6: CN Élite | B6: 480000 | D6: ≈ 40 000 FCFA / mois
A7: MIX DES ADHÉRENTS (répartition par formule)
A8: Part Essentiel | B8: 0.62 | D8: somme des 3 = 100 %
A9: Part Business | B9: 0.3
A10: Part Élite | B10: 0.08
A11: PARAMÈTRES OPÉRATIONNELS
A12: Frais d'adhésion (carte, unique) | B12: 10000 | D12: encaissé à l'inscription
A13: Churn mensuel (attrition) | B13: 0.02 | D13: 2 % des membres partent / mois
A14: Commission partenaires (sur conso.) | B14: 0.08 | D14: CN touche 8 % du CA routé vers partenaires
A15: Coût production carte (unité) | B15: 3500 | D15: carte physique + kit de bienvenue
A16: OPEX MENSUEL FIXE (FCFA)
A17: Plateforme & technologie | B17: 400000 | D17: app membre, CRM, gestion des droits
A18: Équipe & opérations | B18: 2500000 | D18: négociation partenaires, service membre
A19: Marketing & acquisition | B19: 800000 | D19: campagnes, événements, contenus
A20: Frais généraux & juridique | B20: 500000 | D20: bureau, conformité, comptabilité
A21: TOTAL OPEX FIXE / mois | B21: =SUM(B17:B20)

Sheet Modele_Actuariel
A1: MODÈLE ACTUARIEL — coût mutualisé = Σ (probabilité × fréquence × coût unitaire)
A2: Probabilité = % de membres consommant le service dans l'année. 0 % = service non inclus dans la formule.
A3: Service | B3: Valeur faciale /usage | C3: Fréq. /an | D3: Coût unit. CN | E3: Prob. Ess. | F3: Prob. Bus. | G3: Prob. Élite | H3: Coût att. Ess. | I3: Coût att. Bus. | J3: Coût att. Élite | K3: Val. perçue Ess. | L3: Val. perçue Bus. | M3: Val. perçue Élite
A4: Assurance & Prévoyance | B4: 150000 | C4: 1 | D4: 45000 | E4: 0 | F4: 0.2 | G4: 0.4 | H4: =E4*C4*D4 | I4: =F4*C4*D4 | J4: =G4*C4*D4 | K4: =E4*C4*B4 | L4: =F4*C4*B4 | M4: =G4*C4*B4
A5: BTP & Construction | B5: 300000 | C5: 0.5 | D5: 60000 | E5: 0 | F5: 0 | G5: 0.22 | H5: =E5*C5*D5 | I5: =F5*C5*D5 | J5: =G5*C5*D5 | K5: =E5*C5*B5 | L5: =F5*C5*B5 | M5: =G5*C5*B5
A6: Business Lounge | B6: 25000 | C6: 4 | D6: 8000 | E6: 0.04 | F6: 0.18 | G6: 0.55 | H6: =E6*C6*D6 | I6: =F6*C6*D6 | J6: =G6*C6*D6 | K6: =E6*C6*B6 | L6: =F6*C6*B6 | M6: =G6*C6*B6
A7: Aviation | B7: 80000 | C7: 2 | D7: 20000 | E7: 0 | F7: 0.12 | G7: 0.45 | H7: =E7*C7*D7 | I7: =F7*C7*D7 | J7: =G7*C7*D7 | K7: =E7*C7*B7 | L7: =F7*C7*B7 | M7: =G7*C7*B7
A8: Conseil & Expertise compt. | B8: 200000 | C8: 1 | D8: 55000 | E8: 0.12 | F8: 0.28 | G8: 0.55 | H8: =E8*C8*D8 | I8: =F8*C8*D8 | J8: =G8*C8*D8 | K8: =E8*C8*B8 | L8: =F8*C8*B8 | M8: =G8*C8*B8
A9: Santé & Bien-être | B9: 40000 | C9: 2 | D9: 12000 | E9: 0.12 | F9: 0.22 | G9: 0.45 | H9: =E9*C9*D9 | I9: =F9*C9*D9 | J9: =G9*C9*D9 | K9: =E9*C9*B9 | L9: =F9*C9*B9 | M9: =G9*C9*B9
A10: CN Academy — Formation | B10: 100000 | C10: 1 | D10: 25000 | E10: 0.18 | F10: 0.3 | G10: 0.5 | H10: =E10*C10*D10 | I10: =F10*C10*D10 | J10: =G10*C10*D10 | K10: =E10*C10*B10 | L10: =F10*C10*B10 | M10: =G10*C10*B10
A11: Financement & Crédit | B11: 250000 | C11: 0.5 | D11: 50000 | E11: 0 | F11: 0.25 | G11: 0.35 | H11: =E11*C11*D11 | I11: =F11*C11*D11 | J11: =G11*C11*D11 | K11: =E11*C11*B11 | L11: =F11*C11*B11 | M11: =G11*C11*B11
A12: Voyage & Hôtellerie | B12: 60000 | C12: 2 | D12: 18000 | E12: 0 | F12: 0.18 | G12: 0.4 | H12: =E12*C12*D12 | I12: =F12*C12*D12 | J12: =G12*C12*D12 | K12: =E12*C12*B12 | L12: =F12*C12*B12 | M12: =G12*C12*B12
A13: Mobilité Premium | B13: 30000 | C13: 3 | D13: 10000 | E13: 0.06 | F13: 0.15 | G13: 0.35 | H13: =E13*C13*D13 | I13: =F13*C13*D13 | J13: =G13*C13*D13 | K13: =E13*C13*B13 | L13: =F13*C13*B13 | M13: =G13*C13*B13
A14: Juridique & Contentieux | B14: 180000 | C14: 0.4 | D14: 45000 | E14: 0 | F14: 0 | G14: 0.28 | H14: =E14*C14*D14 | I14: =F14*C14*D14 | J14: =G14*C14*D14 | K14: =E14*C14*B14 | L14: =F14*C14*B14 | M14: =G14*C14*B14
A15: Digital & Marketing | B15: 150000 | C15: 0.6 | D15: 40000 | E15: 0.1 | F15: 0.18 | G15: 0.32 | H15: =E15*C15*D15 | I15: =F15*C15*D15 | J15: =G15*C15*D15 | K15: =E15*C15*B15 | L15: =F15*C15*B15 | M15: =G15*C15*B15
... A18: Télécom & Connectivité | B18: 90000 | C18: 1 | D18: 30000 | E18: 0.07 | F18: 0.15 | G18: 0.35 | H18: =E18*C18*D18 | I18: =F18*C18*D18 | J18: =G18*C18*D18 | K18: =E18*C18*B18 | L18: =F18*C18*B18 | M18: =G18*C18*B18
A19: TOTAL / MEMBRE / AN | H19: =SUM(H4:H18) | I19: =SUM(I4:I18) | J19: =SUM(J4:J18) | K19: =SUM(K4:K18) | L19: =SUM(L4:L18) | M19: =SUM(M4:M18)
A21: SYNTHÈSE PAR FORMULE — la clé de l'accessibilité
A22: Indicateur | B22: CN Essentiel | C22: CN Business | D22: CN Élite
A23: Cotisation annuelle | B23: =Hypotheses!B4 | C23: =Hypotheses!B5 | D23: =Hypotheses!B6
A24: Coût mutualisé attendu (réel) | B24: =H19 | C24: =I19 | D24: =J19
A25: Valeur faciale perçue | B25: =K19 | C25: =L19 | D25: =M19
A26: Ratio coût / cotisation (loss ratio) | B26: =H19/Hypotheses!B4 | C26: =I19/Hypotheses!B5 | D26: =J19/Hypotheses!B6
A27: Effet de levier (valeur / prix) | B27: =K19/Hypotheses!B4 | C27: =L19/Hypotheses!B5 | D27: =M19/Hypotheses!B6
A28: Lecture : le membre perçoit une valeur plusieurs fois supérieure au prix, alors que le coût réel mutualisé reste maîtrisé.

Sheet Previsionnel_Membres
A1: PRÉVISIONNEL DES ADHÉRENTS — 36 mois (20 → 850+)
A3: Mois | B3: Total actifs | C3: Essentiel | D3: Business | E3: Élite | F3: Nouveaux | G3: Churn
A4: Mois 1 | B4: 20 | C4: =ROUND(B4*Hypotheses!$B$8,0) | D4: =ROUND(B4*Hypotheses!$B$9,0) | E4: =B4-C4-D4 | F4: =B4 | G4: 0
A5: Mois 2 | B5: 20 | C5: =ROUND(B5*Hypotheses!$B$8,0) | D5: =ROUND(B5*Hypotheses!$B$9,0) | E5: =B5-C5-D5 | F5: =MAX(0,B5-B4)+G5 | G5: =ROUND(B4*Hypotheses!$B$13,0)
A6: Mois 3 | B6: 32 | C6: =ROUND(B6*Hypotheses!$B$8,0) | D6: =ROUND(B6*Hypotheses!$B$9,0) | E6: =B6-C6-D6 | F6: =MAX(0,B6-B5)+G6 | G6: =ROUND(B5*Hypotheses!$B$13,0)
A7: Mois 4 | B7: 48 | C7: =ROUND(B7*Hypotheses!$B$8,0) | D7: =ROUND(B7*Hypotheses!$B$9,0) | E7: =B7-C7-D7 | F7: =MAX(0,B7-B6)+G7 | G7: =ROUND(B6*Hypotheses!$B$13,0)
A8: Mois 5 | B8: 68 | C8: =ROUND(B8*Hypotheses!$B$8,0) | D8: =ROUND(B8*Hypotheses!$B$9,0) | E8: =B8-C8-D8 | F8: =MAX(0,B8-B7)+G8 | G8: =ROUND(B7*Hypotheses!$B$13,0)
A9: Mois 6 | B9: 92 | C9: =ROUND(B9*Hypotheses!$B$8,0) | D9: =ROUND(B9*Hypotheses!$B$9,0) | E9: =B9-C9-D9 | F9: =MAX(0,B9-B8)+G9 | G9: =ROUND(B8*Hypotheses!$B$13,0)
A10: Mois 7 | B10: 120 | C10: =ROUND(B10*Hypotheses!$B$8,0) | D10: =ROUND(B10*Hypotheses!$B$9,0) | E10: =B10-C10-D10 | F10: =MAX(0,B10-B9)+G10 | G10: =ROUND(B9*Hypotheses!$B$13,0)
A11: Mois 8 | B11: 150 | C11: =ROUND(B11*Hypotheses!$B$8,0) | D11: =ROUND(B11*Hypotheses!$B$9,0) | E11: =B11-C11-D11 | F11: =MAX(0,B11-B10)+G11 | G11: =ROUND(B10*Hypotheses!$B$13,0)
A12: Mois 9 | B12: 185 | C12: =ROUND(B12*Hypotheses!$B$8,0) | D12: =ROUND(B12*Hypotheses!$B$9,0) | E12: =B12-C12-D12 | F12: =MAX(0,B12-B11)+G12 | G12: =ROUND(B11*Hypotheses!$B$13,0)
A13: Mois 10 | B13: 222 | C13: =ROUND(B13*Hypotheses!$B$8,0) | D13: =ROUND(B13*Hypotheses!$B$9,0) | E13: =B13-C13-D13 | F13: =MAX(0,B13-B12)+G13 | G13: =ROUND(B12*Hypotheses!$B$13,0)
A14: Mois 11 | B14: 262 | C14: =ROUND(B14*Hypotheses!$B$8,0) | D14: =ROUND(B14*Hypotheses!$B$9,0) | E14: =B14-C14-D14 | F14: =MAX(0,B14-B13)+G14 | G14: =ROUND(B13*Hypotheses!$B$13,0)
A15: Mois 12 | B15: 305 | C15: =ROUND(B15*Hypotheses!$B$8,0) | D15: =ROUND(B15*Hypotheses!$B$9,0) | E15: =B15-C15-D15 | F15: =MAX(0,B15-B14)+G15 | G15: =ROUND(B14*Hypotheses!$B$13,0)
A16: Mois 13 | B16: 350 | C16: =ROUND(B16*Hypotheses!$B$8,0) | D16: =ROUND(B16*Hypotheses!$B$9,0) | E16: =B16-C16-D16 | F16: =MAX(0,B16-B15)+G16 | G16: =ROUND(B15*Hypotheses!$B$13,0)
... A39: Mois 36 | B39: 855 | C39: =ROUND(B39*Hypotheses!$B$8,0) | D39: =ROUND(B39*Hypotheses!$B$9,0) | E39: =B39-C39-D39 | F39: =MAX(0,B39-B38)+G39 | G39: =ROUND(B38*Hypotheses!$B$13,0)

Sheet Compte_Resultat
A1: COMPTE DE RÉSULTAT PRÉVISIONNEL — mensuel, 36 mois (FCFA)
A3: Mois | B3: Adhérents | C3: Rev. abonnements | D3: Rev. frais adh. | E3: Rev. commissions | F3: REVENU TOTAL | G3: Coût services | H3: OPEX + cartes | I3: Résultat mensuel | J3: Résultat cumulé
A4: Mois 1 | B4: ='Previsionnel_Membres'!B4 | C4: =('Previsionnel_Membres'!C4*Hypotheses!$B$4+'Previsionnel_Membres'!D4*Hypotheses!$B$5+'Previsionnel_Membres'!E4*Hypotheses!$B$6)/12 | D4: ='Previsionnel_Membres'!F4*Hypotheses!$B$12 | E4: =('Previsionnel_Membres'!C4*'Modele_Actuariel'!$K$19+'Previsionnel_Membres'!D4*'Modele_Actuariel'!$L$19+'Previsionnel_Membres'!E4*'Modele_Actuariel'!$M$19)/12*Hypotheses!$B$14 | F4: =SUM(C4:E4) | G4: =('Previsionnel_Membres'!C4*'Modele_Actuariel'!$H$19+'Previsionnel_Membres'!D4*'Modele_Actuariel'!$I$19+'Previsionnel_Membres'!E4*'Modele_Actuariel'!$J$19)/12 | H4: =SUM(Hypotheses!$B$17:$B$20)+'Previsionnel_Membres'!F4*Hypotheses!$B$15 | I4: =F4-G4-H4 | J4: =I4
A5: Mois 2 | B5: ='Previsionnel_Membres'!B5 | C5: =('Previsionnel_Membres'!C5*Hypotheses!$B$4+'Previsionnel_Membres'!D5*Hypotheses!$B$5+'Previsionnel_Membres'!E5*Hypotheses!$B$6)/12 | D5: ='Previsionnel_Membres'!F5*Hypotheses!$B$12 | E5: =('Previsionnel_Membres'!C5*'Modele_Actuariel'!$K$19+'Previsionnel_Membres'!D5*'Modele_Actuariel'!$L$19+'Previsionnel_Membres'!E5*'Modele_Actuariel'!$M$19)/12*Hypotheses!$B$14 | F5: =SUM(C5:E5) | G5: =('Previsionnel_Membres'!C5*'Modele_Actuariel'!$H$19+'Previsionnel_Membres'!D5*'Modele_Actuariel'!$I$19+'Previsionnel_Membres'!E5*'Modele_Actuariel'!$J$19)/12 | H5: =SUM(Hypotheses!$B$17:$B$20)+'Previsionnel_Membres'!F5*Hypotheses!$B$15 | I5: =F5-G5-H5 | J5: =J4+I5
A6: Mois 3 | B6: ='Previsionnel_Membres'!B6 | C6: =('Previsionnel_Membres'!C6*Hypotheses!$B$4+'Previsionnel_Membres'!D6*Hypotheses!$B$5+'Previsionnel_Membres'!E6*Hypotheses!$B$6)/12 | D6: ='Previsionnel_Membres'!F6*Hypotheses!$B$12 | E6: =('Previsionnel_Membres'!C6*'Modele_Actuariel'!$K$19+'Previsionnel_Membres'!D6*'Modele_Actuariel'!$L$19+'Previsionnel_Membres'!E6*'Modele_Actuariel'!$M$19)/12*Hypotheses!$B$14 | F6: =SUM(C6:E6) | G6: =('Previsionnel_Membres'!C6*'Modele_Actuariel'!$H$19+'Previsionnel_Membres'!D6*'Modele_Actuariel'!$I$19+'Previsionnel_Membres'!E6*'Modele_Actuariel'!$J$19)/12 | H6: =SUM(Hypotheses!$B$17:$B$20)+'Previsionnel_Membres'!F6*Hypotheses!$B$15 | I6: =F6-G6-H6 | J6: =J5+I6
A7: Mois 4 | B7: ='Previsionnel_Membres'!B7 | C7: =('Previsionnel_Membres'!C7*Hypotheses!$B$4+'Previsionnel_Membres'!D7*Hypotheses!$B$5+'Previsionnel_Membres'!E7*Hypotheses!$B$6)/12 | D7: ='Previsionnel_Membres'!F7*Hypotheses!$B$12 | E7: =('Previsionnel_Membres'!C7*'Modele_Actuariel'!$K$19+'Previsionnel_Membres'!D7*'Modele_Actuariel'!$L$19+'Previsionnel_Membres'!E7*'Modele_Actuariel'!$M$19)/12*Hypotheses!$B$14 | F7: =SUM(C7:E7) | G7: =('Previsionnel_Membres'!C7*'Modele_Actuariel'!$H$19+'Previsionnel_Membres'!D7*'Modele_Actuariel'!$I$19+'Previsionnel_Membres'!E7*'Modele_Actuariel'!$J$19)/12 | H7: =SUM(Hypotheses!$B$17:$B$20)+'Previsionnel_Membres'!F7*Hypotheses!$B$15 | I7: =F7-G7-H7 | J7: =J6+I7
A8: Mois 5 | B8: ='Previsionnel_Membres'!B8 | C8: =('Previsionnel_Membres'!C8*Hypotheses!$B$4+'Previsionnel_Membres'!D8*Hypotheses!$B$5+'Previsionnel_Membres'!E8*Hypotheses!$B$6)/12 | D8: ='Previsionnel_Membres'!F8*Hypotheses!$B$12 | E8: =('Previsionnel_Membres'!C8*'Modele_Actuariel'!$K$19+'Previsionnel_Membres'!D8*'Modele_Actuariel'!$L$19+'Previsionnel_Membres'!E8*'Modele_Actuariel'!$M$19)/12*Hypotheses!$B$14 | F8: =SUM(C8:E8) | G8: =('Previsionnel_Membres'!C8*'Modele_Actuariel'!$H$19+'Previsionnel_Membres'!D8*'Modele_Actuariel'!$I$19+'Previsionnel_Membres'!E8*'Modele_Actuariel'!$J$19)/12 | H8: =SUM(Hypotheses!$B$17:$B$20)+'Previsionnel_Membres'!F8*Hypotheses!$B$15 | I8: =F8-G8-H8 | J8: =J7+I8
A9: Mois 6 | B9: ='Previsionnel_Membres'!B9 | C9: =('Previsionnel_Membres'!C9*Hypotheses!$B$4+'Previsionnel_Membres'!D9*Hypotheses!$B$5+'Previsionnel_Membres'!E9*Hypotheses!$B$6)/12 | D9: ='Previsionnel_Membres'!F9*Hypotheses!$B$12 | E9: =('Previsionnel_Membres'!C9*'Modele_Actuariel'!$K$19+'Previsionnel_Membres'!D9*'Modele_Actuariel'!$L$19+'Previsionnel_Membres'!E9*'Modele_Actuariel'!$M$19)/12*Hypotheses!$B$14 | F9: =SUM(C9:E9) | G9: =('Previsionnel_Membres'!C9*'Modele_Actuariel'!$H$19+'Previsionnel_Membres'!D9*'Modele_Actuariel'!$I$19+'Previsionnel_Membres'!E9*'Modele_Actuariel'!$J$19)/12 | H9: =SUM(Hypotheses!$B$17:$B$20)+'Previsionnel_Membres'!F9*Hypotheses!$B$15 | I9: =F9-G9-H9 | J9: =J8+I9
A10: Mois 7 | B10: ='Previsionnel_Membres'!B10 | C10: =('Previsionnel_Membres'!C10*Hypotheses!$B$4+'Previsionnel_Membres'!D10*Hypotheses!$B$5+'Previsionnel_Membres'!E10*Hypotheses!$B$6)/12 | D10: ='Previsionnel_Membres'!F10*Hypotheses!$B$12 | E10: =('Previsionnel_Membres'!C10*'Modele_Actuariel'!$K$19+'Previsionnel_Membres'!D10*'Modele_Actuariel'!$L$19+'Previsionnel_Membres'!E10*'Modele_Actuariel'!$M$19)/12*Hypotheses!$B$14 | F10: =SUM(C10:E10) | G10: =('Previsionnel_Membres'!C10*'Modele_Actuariel'!$H$19+'Previsionnel_Membres'!D10*'Modele_Actuariel'!$I$19+'Previsionnel_Membres'!E10*'Modele_Actuariel'!$J$19)/12 | H10: =SUM(Hypotheses!$B$17:$B$20)+'Previsionnel_Membres'!F10*Hypotheses!$B$15 | I10: =F10-G10-H10 | J10: =J9+I10
A11: Mois 8 | B11: ='Previsionnel_Membres'!B11 | C11: =('Previsionnel_Membres'!C11*Hypotheses!$B$4+'Previsionnel_Membres'!D11*Hypotheses!$B$5+'Previsionnel_Membres'!E11*Hypotheses!$B$6)/12 | D11: ='Previsionnel_Membres'!F11*Hypotheses!$B$12 | E11: =('Previsionnel_Membres'!C11*'Modele_Actuariel'!$K$19+'Previsionnel_Membres'!D11*'Modele_Actuariel'!$L$19+'Previsionnel_Membres'!E11*'Modele_Actuariel'!$M$19)/12*Hypotheses!$B$14 | F11: =SUM(C11:E11) | G11: =('Previsionnel_Membres'!C11*'Modele_Actuariel'!$H$19+'Previsionnel_Membres'!D11*'Modele_Actuariel'!$I$19+'Previsionnel_Membres'!E11*'Modele_Actuariel'!$J$19)/12 | H11: =SUM(Hypotheses!$B$17:$B$20)+'Previsionnel_Membres'!F11*Hypotheses!$B$15 | I11: =F11-G11-H11 | J11: =J10+I11
A12: Mois 9 | B12: ='Previsionnel_Membres'!B12 | C12: =('Previsionnel_Membres'!C12*Hypotheses!$B$4+'Previsionnel_Membres'!D12*Hypotheses!$B$5+'Previsionnel_Membres'!E12*Hypotheses!$B$6)/12 | D12: ='Previsionnel_Membres'!F12*Hypotheses!$B$12 | E12: =('Previsionnel_Membres'!C12*'Modele_Actuariel'!$K$19+'Previsionnel_Membres'!D12*'Modele_Actuariel'!$L$19+'Previsionnel_Membres'!E12*'Modele_Actuariel'!$M$19)/12*Hypotheses!$B$14 | F12: =SUM(C12:E12) | G12: =('Previsionnel_Membres'!C12*'Modele_Actuariel'!$H$19+'Previsionnel_Membres'!D12*'Modele_Actuariel'!$I$19+'Previsionnel_Membres'!E12*'Modele_Actuariel'!$J$19)/12 | H12: =SUM(Hypotheses!$B$17:$B$20)+'Previsionnel_Membres'!F12*Hypotheses!$B$15 | I12: =F12-G12-H12 | J12: =J11+I12
A13: Mois 10 | B13: ='Previsionnel_Membres'!B13 | C13: =('Previsionnel_Membres'!C13*Hypotheses!$B$4+'Previsionnel_Membres'!D13*Hypotheses!$B$5+'Previsionnel_Membres'!E13*Hypotheses!$B$6)/12 | D13: ='Previsionnel_Membres'!F13*Hypotheses!$B$12 | E13: =('Previsionnel_Membres'!C13*'Modele_Actuariel'!$K$19+'Previsionnel_Membres'!D13*'Modele_Actuariel'!$L$19+'Previsionnel_Membres'!E13*'Modele_Actuariel'!$M$19)/12*Hypotheses!$B$14 | F13: =SUM(C13:E13) | G13: =('Previsionnel_Membres'!C13*'Modele_Actuariel'!$H$19+'Previsionnel_Membres'!D13*'Modele_Actuariel'!$I$19+'Previsionnel_Membres'!E13*'Modele_Actuariel'!$J$19)/12 | H13: =SUM(Hypotheses!$B$17:$B$20)+'Previsionnel_Membres'!F13*Hypotheses!$B$15 | I13: =F13-G13-H13 | J13: =J12+I13
A14: Mois 11 | B14: ='Previsionnel_Membres'!B14 | C14: =('Previsionnel_Membres'!C14*Hypotheses!$B$4+'Previsionnel_Membres'!D14*Hypotheses!$B$5+'Previsionnel_Membres'!E14*Hypotheses!$B$6)/12 | D14: ='Previsionnel_Membres'!F14*Hypotheses!$B$12 | E14: =('Previsionnel_Membres'!C14*'Modele_Actuariel'!$K$19+'Previsionnel_Membres'!D14*'Modele_Actuariel'!$L$19+'Previsionnel_Membres'!E14*'Modele_Actuariel'!$M$19)/12*Hypotheses!$B$14 | F14: =SUM(C14:E14) | G14: =('Previsionnel_Membres'!C14*'Modele_Actuariel'!$H$19+'Previsionnel_Membres'!D14*'Modele_Actuariel'!$I$19+'Previsionnel_Membres'!E14*'Modele_Actuariel'!$J$19)/12 | H14: =SUM(Hypotheses!$B$17:$B$20)+'Previsionnel_Membres'!F14*Hypotheses!$B$15 | I14: =F14-G14-H14 | J14: =J13+I14
A15: Mois 12 | B15: ='Previsionnel_Membres'!B15 | C15: =('Previsionnel_Membres'!C15*Hypotheses!$B$4+'Previsionnel_Membres'!D15*Hypotheses!$B$5+'Previsionnel_Membres'!E15*Hypotheses!$B$6)/12 | D15: ='Previsionnel_Membres'!F15*Hypotheses!$B$12 | E15: =('Previsionnel_Membres'!C15*'Modele_Actuariel'!$K$19+'Previsionnel_Membres'!D15*'Modele_Actuariel'!$L$19+'Previsionnel_Membres'!E15*'Modele_Actuariel'!$M$19)/12*Hypotheses!$B$14 | F15: =SUM(C15:E15) | G15: =('Previsionnel_Membres'!C15*'Modele_Actuariel'!$H$19+'Previsionnel_Membres'!D15*'Modele_Actuariel'!$I$19+'Previsionnel_Membres'!E15*'Modele_Actuariel'!$J$19)/12 | H15: =SUM(Hypotheses!$B$17:$B$20)+'Previsionnel_Membres'!F15*Hypotheses!$B$15 | I15: =F15-G15-H15 | J15: =J14+I15
A16: Mois 13 | B16: ='Previsionnel_Membres'!B16 | C16: =('Previsionnel_Membres'!C16*Hypotheses!$B$4+'Previsionnel_Membres'!D16*Hypotheses!$B$5+'Previsionnel_Membres'!E16*Hypotheses!$B$6)/12 | D16: ='Previsionnel_Membres'!F16*Hypotheses!$B$12 | E16: =('Previsionnel_Membres'!C16*'Modele_Actuariel'!$K$19+'Previsionnel_Membres'!D16*'Modele_Actuariel'!$L$19+'Previsionnel_Membres'!E16*'Modele_Actuariel'!$M$19)/12*Hypotheses!$B$14 | F16: =SUM(C16:E16) | G16: =('Previsionnel_Membres'!C16*'Modele_Actuariel'!$H$19+'Previsionnel_Membres'!D16*'Modele_Actuariel'!$I$19+'Previsionnel_Membres'!E16*'Modele_Actuariel'!$J$19)/12 | H16: =SUM(Hypotheses!$B$17:$B$20)+'Previsionnel_Membres'!F16*Hypotheses!$B$15 | I16: =F16-G16-H16 | J16: =J15+I16
... A39: Mois 36 | B39: ='Previsionnel_Membres'!B39 | C39: =('Previsionnel_Membres'!C39*Hypotheses!$B$4+'Previsionnel_Membres'!D39*Hypotheses!$B$5+'Previsionnel_Membres'!E39*Hypotheses!$B$6)/12 | D39: ='Previsionnel_Membres'!F39*Hypotheses!$B$12 | E39: =('Previsionnel_Membres'!C39*'Modele_Actuariel'!$K$19+'Previsionnel_Membres'!D39*'Modele_Actuariel'!$L$19+'Previsionnel_Membres'!E39*'Modele_Actuariel'!$M$19)/12*Hypotheses!$B$14 | F39: =SUM(C39:E39) | G39: =('Previsionnel_Membres'!C39*'Modele_Actuariel'!$H$19+'Previsionnel_Membres'!D39*'Modele_Actuariel'!$I$19+'Previsionnel_Membres'!E39*'Modele_Actuariel'!$J$19)/12 | H39: =SUM(Hypotheses!$B$17:$B$20)+'Previsionnel_Membres'!F39*Hypotheses!$B$15 | I39: =F39-G39-H39 | J39: =J38+I39

Sheet Tableau_de_Bord
A1: TABLEAU DE BORD
B3: INDICATEURS CLÉS
B4: ARR indicatif (abonnements, mois 36 ×12) | E4: ='Compte_Resultat'!C39*12
B5: Revenu total — année 3 (mois 25-36) | E5: =SUM('Compte_Resultat'!F28:F39)
B6: Résultat cumulé à 36 mois | E6: ='Compte_Resultat'!J39
B7: Coût d'acquisition implicite / membre | E7: =Hypotheses!B19/ MAX(1,'Previsionnel_Membres'!F39)
B8: Revenu moyen / membre / mois (mois 36) | E8: ='Compte_Resultat'!F39/'Compte_Resultat'!B39
B9: Loss ratio moyen pondéré | E9: =('Modele_Actuariel'!H19*Hypotheses!B8+'Modele_Actuariel'!I19*Hypotheses!B9+'Modele_Actuariel'!J19*Hypotheses!B10)/(Hypotheses!B4*Hypotheses!B8+Hypotheses!B5*Hypotheses!B9+Hypotheses!B6*Hypotheses!B10)

Sheet Feuille_de_Route
A1: FEUILLE DE ROUTE — déploiement en 4 phases
A3: Phase | B3: Période | C3: Actions clés | D3: Objectif
A4: Phase 1 Amorçage | B4: Mois 1-2 | C4: Signer 5-8 partenaires fondateurs (assurance, conseil, lounge, télécom). Émettre les premières cartes. 20 membres pilotes issus du réseau CN. | D4: 20 membres actifs
A5: Phase 2 Structuration | B5: Mois 3-6 | C5: App membre + CRM. Élargir à 10 branches. Preuve d'usage & témoignages. Grille de commissions partenaires. | D5: ~100 membres
A6: Phase 3 Accélération | B6: Mois 7-18 | C6: Campagnes ciblées (CNP, chambres, DER/FJ). Les 15 branches actives. Événements networking mensuels. | D6: Cap des 500 franchi
A7: Phase 4 Expansion régionale | B7: Mois 19-36 | C7: Ouverture UEMOA (Abidjan, Bamako, Cotonou). Formules corporate multi-cartes. Programme de parrainage. | D7: 850+ membres
A9: PROCHAINES ACTIONS IMMÉDIATES
A10: ☐ Valider la grille tarifaire et le mix cible (feuille Hypotheses).
A11: ☐ Prioriser 5 partenaires fondateurs et négocier les taux de remise / commission.
A12: ☐ Concevoir la carte (physique + digitale) et le kit de bienvenue.
A13: ☐ Rédiger les conditions d'adhésion et la charte partenaires.
A14: ☐ Lancer le pilote 20 membres issus du réseau CN pour affiner les probabilités réelles de consommation.
